Workbook

Sheet Executive Dashboard
A1: APPLE FINANCIAL INTELLIGENCE
A2: FY2023–FY2025 • Growth • Profitability • Product Mix • Geography
A4: VIEW YEAR | B4: 2025 | D4: COMPARE YEAR | E4: 2024
A6: REVENUE | C6: GROSS PROFIT | E6: OPERATING INCOME | G6: NET INCOME | I6: GROSS MARGIN | K6: NET MARGIN
A7: =INDEX('KPI Summary'!$B$2:$B$4,MATCH($B$4,'KPI Summary'!$A$2:$A$4,0)) | C7: =INDEX('KPI Summary'!$C$2:$C$4,MATCH($B$4,'KPI Summary'!$A$2:$A$4,0)) | E7: =INDEX('KPI Summary'!$D$2:$D$4,MATCH($B$4,'KPI Summary'!$A$2:$A$4,0)) | G7: =INDEX('KPI Summary'!$E$2:$E$4,MATCH($B$4,'KPI Summary'!$A$2:$A$4,0)) | I7: =INDEX('KPI Summary'!$F$2:$F$4,MATCH($B$4,'KPI Summary'!$A$2:$A$4,0)) | K7: =INDEX('KPI Summary'!$H$2:$H$4,MATCH($B$4,'KPI Summary'!$A$2:$A$4,0))
A10: SELECTED YEAR VS COMPARISON | G10: EXECUTIVE TAKEAWAYS
A11: Metric | B11: Selected | C11: Comparison | D11: Δ | E11: Δ % | G11: • Topline: FY2025 revenue reached approximately $416.2B.
A12: Revenue | B12: =INDEX('KPI Summary'!$B$2:$B$4,MATCH($B$4,'KPI Summary'!$A$2:$A$4,0)) | C12: =INDEX('KPI Summary'!$B$2:$B$4,MATCH($E$4,'KPI Summary'!$A$2:$A$4,0)) | D12: =B12-C12 | E12: =IFERROR(B12/C12-1,"") | G12: • Profitability: net income rebounded materially in FY2025.
A13: Gross Profit | B13: =INDEX('KPI Summary'!$C$2:$C$4,MATCH($B$4,'KPI Summary'!$A$2:$A$4,0)) | C13: =INDEX('KPI Summary'!$C$2:$C$4,MATCH($E$4,'KPI Summary'!$A$2:$A$4,0)) | D13: =B13-C13 | E13: =IFERROR(B13/C13-1,"") | G13: • Mix: Services continued expanding while iPhone remained the largest category.
A14: Operating Income | B14: =INDEX('KPI Summary'!$D$2:$D$4,MATCH($B$4,'KPI Summary'!$A$2:$A$4,0)) | C14: =INDEX('KPI Summary'!$D$2:$D$4,MATCH($E$4,'KPI Summary'!$A$2:$A$4,0)) | D14: =B14-C14 | E14: =IFERROR(B14/C14-1,"") | G14: • Geography: Europe and the Americas grew across the three-year window.
A15: Net Income | B15: =INDEX('KPI Summary'!$E$2:$E$4,MATCH($B$4,'KPI Summary'!$A$2:$A$4,0)) | C15: =INDEX('KPI Summary'!$E$2:$E$4,MATCH($E$4,'KPI Summary'!$A$2:$A$4,0)) | D15: =B15-C15 | E15: =IFERROR(B15/C15-1,"") | G15: • Exception: Greater China revenue declined over the period.
A16: Net Margin | B16: =INDEX('KPI Summary'!$H$2:$H$4,MATCH($B$4,'KPI Summary'!$A$2:$A$4,0)) | C16: =INDEX('KPI Summary'!$H$2:$H$4,MATCH($E$4,'KPI Summary'!$A$2:$A$4,0)) | D16: =B16-C16 | E16: =IFERROR(B16/C16-1,"")
A53: SOURCE & SCOPE • Apple FY2025 Form 10-K / SEC • FY2023–FY2025 • USD millions • Margins and YoY metrics are calculated • No forecasts
A55: =HYPERLINK("#'P&L'!A1","Data & Tables") | D55: =HYPERLINK("#'Product Revenue'!A1","Product Data") | G55: =HYPERLINK("#'Geography Revenue'!A1","Geography") | J55: =HYPERLINK("#'KPI Summary'!A1","KPI Data") | M55: =HYPERLINK("#'References'!A1","Sources & Citations")

Sheet Control Center
A1: APPLE FINANCIAL INTELLIGENCE — CONTROL CENTER
A4: Interactive controls
A5: Selected fiscal year | B5: 2025
A6: Comparison year | B6: 2024
A8: Revenue | C8: Gross Profit | E8: Operating Income | G8: Net Income | I8: Gross Margin | K8: Net Margin
A9: =INDEX('KPI Summary'!$B$2:$B$4,MATCH($B$5,'KPI Summary'!$A$2:$A$4,0)) | C9: =INDEX('KPI Summary'!$C$2:$C$4,MATCH($B$5,'KPI Summary'!$A$2:$A$4,0)) | E9: =INDEX('KPI Summary'!$D$2:$D$4,MATCH($B$5,'KPI Summary'!$A$2:$A$4,0)) | G9: =INDEX('KPI Summary'!$E$2:$E$4,MATCH($B$5,'KPI Summary'!$A$2:$A$4,0)) | I9: =INDEX('KPI Summary'!$F$2:$F$4,MATCH($B$5,'KPI Summary'!$A$2:$A$4,0)) | K9: =INDEX('KPI Summary'!$H$2:$H$4,MATCH($B$5,'KPI Summary'!$A$2:$A$4,0))
A12: Selected-year comparison | G12: Three-year trend
A13: Metric | B13: Selected Year | C13: Comparison Year | D13: Change | E13: Change % | G13: Year | H13: Revenue | I13: Net Income | J13: Gross Margin | K13: Net Margin
A14: Revenue | B14: =INDEX('KPI Summary'!$B$2:$B$4,MATCH($B$5,'KPI Summary'!$A$2:$A$4,0)) | C14: =INDEX('KPI Summary'!$B$2:$B$4,MATCH($B$6,'KPI Summary'!$A$2:$A$4,0)) | D14: =B14-C14 | E14: =IFERROR(B14/C14-1,"") | G14: 2023 | H14: =INDEX('KPI Summary'!$B$2:$B$4,MATCH(G14,'KPI Summary'!$A$2:$A$4,0)) | I14: =INDEX('KPI Summary'!$E$2:$E$4,MATCH(G14,'KPI Summary'!$A$2:$A$4,0)) | J14: =INDEX('KPI Summary'!$F$2:$F$4,MATCH(G14,'KPI Summary'!$A$2:$A$4,0)) | K14: =INDEX('KPI Summary'!$H$2:$H$4,MATCH(G14,'KPI Summary'!$A$2:$A$4,0))
A15: Gross Profit | B15: =INDEX('KPI Summary'!$C$2:$C$4,MATCH($B$5,'KPI Summary'!$A$2:$A$4,0)) | C15: =INDEX('KPI Summary'!$C$2:$C$4,MATCH($B$6,'KPI Summary'!$A$2:$A$4,0)) | D15: =B15-C15 | E15: =IFERROR(B15/C15-1,"") | G15: 2024 | H15: =INDEX('KPI Summary'!$B$2:$B$4,MATCH(G15,'KPI Summary'!$A$2:$A$4,0)) | I15: =INDEX('KPI Summary'!$E$2:$E$4,MATCH(G15,'KPI Summary'!$A$2:$A$4,0)) | J15: =INDEX('KPI Summary'!$F$2:$F$4,MATCH(G15,'KPI Summary'!$A$2:$A$4,0)) | K15: =INDEX('KPI Summary'!$H$2:$H$4,MATCH(G15,'KPI Summary'!$A$2:$A$4,0))
A16: Operating Income | B16: =INDEX('KPI Summary'!$D$2:$D$4,MATCH($B$5,'KPI Summary'!$A$2:$A$4,0)) | C16: =INDEX('KPI Summary'!$D$2:$D$4,MATCH($B$6,'KPI Summary'!$A$2:$A$4,0)) | D16: =B16-C16 | E16: =IFERROR(B16/C16-1,"") | G16: 2025 | H16: =INDEX('KPI Summary'!$B$2:$B$4,MATCH(G16,'KPI Summary'!$A$2:$A$4,0)) | I16: =INDEX('KPI Summary'!$E$2:$E$4,MATCH(G16,'KPI Summary'!$A$2:$A$4,0)) | J16: =INDEX('KPI Summary'!$F$2:$F$4,MATCH(G16,'KPI Summary'!$A$2:$A$4,0)) | K16: =INDEX('KPI Summary'!$H$2:$H$4,MATCH(G16,'KPI Summary'!$A$2:$A$4,0))
A17: Net Income | B17: =INDEX('KPI Summary'!$E$2:$E$4,MATCH($B$5,'KPI Summary'!$A$2:$A$4,0)) | C17: =INDEX('KPI Summary'!$E$2:$E$4,MATCH($B$6,'KPI Summary'!$A$2:$A$4,0)) | D17: =B17-C17 | E17: =IFERROR(B17/C17-1,"")
A18: Gross Margin | B18: =INDEX('KPI Summary'!$F$2:$F$4,MATCH($B$5,'KPI Summary'!$A$2:$A$4,0)) | C18: =INDEX('KPI Summary'!$F$2:$F$4,MATCH($B$6,'KPI Summary'!$A$2:$A$4,0)) | D18: =B18-C18 | E18: =IFERROR(B18/C18-1,"")
A19: Net Margin | B19: =INDEX('KPI Summary'!$H$2:$H$4,MATCH($B$5,'KPI Summary'!$A$2:$A$4,0)) | C19: =INDEX('KPI Summary'!$H$2:$H$4,MATCH($B$6,'KPI Summary'!$A$2:$A$4,0)) | D19: =B19-C19 | E19: =IFERROR(B19/C19-1,"")

Sheet README
A1: Apple Financial Intelligence — Excel Analysis Pack
A3: Purpose | B3: Excel companion to the interactive dashboard. Includes reviewed financial data, KPI calculations, analytical tables, and native Excel charts.
A4: Source | B4: Apple Inc. FY2025 Form 10-K, U.S. SEC
A5: Period | B5: FY2023–FY2025
A6: Units | B6: USD millions unless otherwise stated
A7: Cleaning status | B7: Reviewed dataset: no missing values or duplicate rows identified; numeric fields standardized.
A9: Workflow followed | B9: Profile → clean/review → compare → break down → re-measure → exceptions → select visuals → dashboard
A10: Dashboard visuals | B10: Revenue/profit trend; revenue composition; product trend; geographic trend; margin profile; operating-expense intensity

Sheet P&L
A1: Year | B1: Revenue | C1: Gross Profit | D1: Operating Income | E1: Net Income | F1: R&D | G1: SG&A
A2: 2023 | B2: 383285 | C2: 169148 | D2: 114301 | E2: 96995 | F2: 29915 | G2: 24932
A3: 2024 | B3: 391035 | C3: 180683 | D3: 123216 | E3: 93736 | F3: 31370 | G3: 26097
A4: 2025 | B4: 416161 | C4: 195201 | D4: 133050 | E4: 112010 | F4: 34550 | G4: 27601

Sheet Product Revenue
A1: Year | B1: iPhone | C1: Mac | D1: iPad | E1: Wearables, Home & Accessories | F1: Services
A2: 2023 | B2: 200583 | C2: 29357 | D2: 28300 | E2: 39845 | F2: 85200
A3: 2024 | B3: 201183 | C3: 29984 | D3: 26694 | E3: 37005 | F3: 96169
A4: 2025 | B4: 209586 | C4: 33708 | D4: 28023 | E4: 35686 | F4: 109158

Sheet Geography Revenue
A1: Year | B1: Americas | C1: Europe | D1: Greater China | E1: Japan | F1: Rest of Asia Pacific
A2: 2023 | B2: 162560 | C2: 94294 | D2: 72559 | E2: 24257 | F2: 29615
A3: 2024 | B3: 167045 | C3: 101328 | D3: 66952 | E3: 25052 | F3: 30658
A4: 2025 | B4: 178353 | C4: 111032 | D4: 64377 | E4: 28703 | F4: 33696

Sheet KPI Summary
A1: Year | B1: Revenue | C1: Gross Profit | D1: Operating Income | E1: Net Income | F1: Gross Margin | G1: Operating Margin | H1: Net Margin | I1: Revenue YoY | J1: Net Income YoY
A2: 2023 | B2: 383285 | C2: 169148 | D2: 114301 | E2: 96995 | F2: 0.4413113 | G2: 0.29821412 | H2: 0.25306234
A3: 2024 | B3: 391035 | C3: 180683 | D3: 123216 | E3: 93736 | F3: 0.4620635 | G3: 0.31510223 | H3: 0.23971256 | I3: 0.020219941 | J3: -0.03359967
A4: 2025 | B4: 416161 | C4: 195201 | D4: 133050 | E4: 112010 | F4: 0.46905164 | G4: 0.319708 | H4: 0.26915064 | I4: 0.064255118 | J4: 0.19495178

Sheet Pivot Detail
A1: Year | B1: Dimension | C1: Category | D1: Value (USD millions) | E1: Source
A2: 2023 | B2: P&L | C2: Revenue | D2: 383285 | E2: Apple FY2025 Form 10-K / SEC
A3: 2023 | B3: P&L | C3: Gross Profit | D3: 169148 | E3: Apple FY2025 Form 10-K / SEC
A4: 2023 | B4: P&L | C4: Operating Income | D4: 114301 | E4: Apple FY2025 Form 10-K / SEC
A5: 2023 | B5: P&L | C5: Net Income | D5: 96995 | E5: Apple FY2025 Form 10-K / SEC
A6: 2023 | B6: P&L | C6: R&D | D6: 29915 | E6: Apple FY2025 Form 10-K / SEC
A7: 2023 | B7: P&L | C7: SG&A | D7: 24932 | E7: Apple FY2025 Form 10-K / SEC
A8: 2024 | B8: P&L | C8: Revenue | D8: 391035 | E8: Apple FY2025 Form 10-K / SEC
A9: 2024 | B9: P&L | C9: Gross Profit | D9: 180683 | E9: Apple FY2025 Form 10-K / SEC
A10: 2024 | B10: P&L | C10: Operating Income | D10: 123216 | E10: Apple FY2025 Form 10-K / SEC
A11: 2024 | B11: P&L | C11: Net Income | D11: 93736 | E11: Apple FY2025 Form 10-K / SEC
A12: 2024 | B12: P&L | C12: R&D | D12: 31370 | E12: Apple FY2025 Form 10-K / SEC
A13: 2024 | B13: P&L | C13: SG&A | D13: 26097 | E13: Apple FY2025 Form 10-K / SEC
... A49: 2025 | B49: Geography Revenue | C49: Rest of Asia Pacific | D49: 33696 | E49: Apple FY2025 Form 10-K / SEC

Sheet Excel Dashboard
A1: Apple Financial Intelligence — Excel Dashboard
A2: Interactive Excel companion • use Control Center for year selection and comparison. | L2: =HYPERLINK("#'Control Center'!A1","← Control Center")
A3: Revenue | C3: Net Income | E3: Gross Margin | G3: Operating Margin | I3: Net Margin | L3: =HYPERLINK("#'KPI Summary'!A1","KPI Summary")
A4: 416161 | C4: 112010 | E4: 0.46905164 | G4: 0.319708 | I4: 0.26915064 | L4: =HYPERLINK("#'Pivot Detail'!A1","Pivot Detail")
L5: =HYPERLINK("#'Data Dictionary'!A1","Data Dictionary")
A39: Note: Excel charts are native chart objects; the HTML dashboard provides the richer hover/click interaction required for the web submission.

Sheet Data Dictionary
A1: DATA DICTIONARY & METHODOLOGY
A2: Field / Concept | B2: Definition | C2: Unit | D2: Treatment
A3: Revenue | B3: Total reported net sales for the fiscal year | C3: USD millions | D3: Reported
A4: Gross Profit | B4: Revenue less cost of sales | C4: USD millions | D4: Reported
A5: Operating Income | B5: Operating profit after operating expenses | C5: USD millions | D5: Reported
A6: Net Income | B6: Net earnings attributable to Apple | C6: USD millions | D6: Reported
A7: Gross Margin | B7: Gross Profit / Revenue | C7: % | D7: Calculated
A8: Operating Margin | B8: Operating Income / Revenue | C8: % | D8: Calculated
A9: Net Margin | B9: Net Income / Revenue | C9: % | D9: Calculated
A10: YoY Growth | B10: Current year / prior year - 1 | C10: % | D10: Calculated
A11: Product Revenue | B11: Reported net sales by product/service category | C11: USD millions | D11: Reported
A12: Geography Revenue | B12: Reported net sales by geographic region | C12: USD millions | D12: Reported
A16: Source | B16: Apple Inc. FY2025 Form 10-K, U.S. SEC
A17: Period | B17: FY2023–FY2025
A18: Important note | B18: The HTML dashboard is the richer interactive web layer; this workbook is the editable Excel analysis layer with native tables, formulas, validation controls and charts.

Sheet References
A1: DATA SOURCES & CITATIONS
A3: Primary source | B3: Apple Inc. — FY2025 Form 10-K
A4: Filing period | B4: Fiscal year ended September 27, 2025
A5: Filing / issuer | B5: Apple Inc.
A6: Regulator | B6: U.S. Securities and Exchange Commission (SEC)
A8: SEC filing | B8: =HYPERLINK("https://www.sec.gov/Archives/edgar/data/320193/000032019325000079/aapl-20250927.htm","Open Apple FY2025 Form 10-K at SEC")
A9: Apple Investor Relations | B9: =HYPERLINK("https://investor.apple.com/investor-relations/sec-filings/default.aspx?language=en-US","Open Apple SEC Filings page")
A11: Data used | B11: FY2023–FY2025 revenue, gross profit, operating income, net income, R&D, SG&A, product revenue and geographic revenue.
A12: Calculated metrics | B12: Gross margin, operating margin, net margin, revenue share and YoY growth are calculated from reported figures.
A13: Units | B13: USD millions unless otherwise stated.
A14: Forecasts | B14: None.
